odoo/addons/hr_holidays_imposed_days/README.rst
odoo/addons/hr_holidays_imposed_days/__init__.py
odoo/addons/hr_holidays_imposed_days/__manifest__.py
odoo/addons/hr_holidays_imposed_days/i18n/ar.po
odoo/addons/hr_holidays_imposed_days/i18n/de.po
odoo/addons/hr_holidays_imposed_days/i18n/es.po
odoo/addons/hr_holidays_imposed_days/i18n/fi.po
odoo/addons/hr_holidays_imposed_days/i18n/fr.po
odoo/addons/hr_holidays_imposed_days/i18n/hr.po
odoo/addons/hr_holidays_imposed_days/i18n/hr_HR.po
odoo/addons/hr_holidays_imposed_days/i18n/it.po
odoo/addons/hr_holidays_imposed_days/i18n/nl_NL.po
odoo/addons/hr_holidays_imposed_days/i18n/pl.po
odoo/addons/hr_holidays_imposed_days/i18n/pt_BR.po
odoo/addons/hr_holidays_imposed_days/i18n/ro.po
odoo/addons/hr_holidays_imposed_days/i18n/sl.po
odoo/addons/hr_holidays_imposed_days/models/__init__.py
odoo/addons/hr_holidays_imposed_days/models/hr_employee.py
odoo/addons/hr_holidays_imposed_days/models/hr_holidays_imposed.py
odoo/addons/hr_holidays_imposed_days/security/ir.model.access.csv
odoo/addons/hr_holidays_imposed_days/tests/__init__.py
odoo/addons/hr_holidays_imposed_days/tests/test_hr_holidays_imposed.py
odoo/addons/hr_holidays_imposed_days/views/hr_holidays_imposed_view.xml
odoo11_addon_hr_holidays_imposed_days-11.0.1.0.0.dist-info/DESCRIPTION.rst
odoo11_addon_hr_holidays_imposed_days-11.0.1.0.0.dist-info/METADATA
odoo11_addon_hr_holidays_imposed_days-11.0.1.0.0.dist-info/RECORD
odoo11_addon_hr_holidays_imposed_days-11.0.1.0.0.dist-info/WHEEL
odoo11_addon_hr_holidays_imposed_days-11.0.1.0.0.dist-info/metadata.json
odoo11_addon_hr_holidays_imposed_days-11.0.1.0.0.dist-info/top_level.txt
